cdk_constants/_jsii/__init__.py
cdk_constants/_jsii/cdk-constants@2.1.2.jsii.tgz
cdk_constants-2.1.2.dist-info/METADATA
cdk_constants-2.1.2.dist-info/WHEEL
cdk_constants-2.1.2.dist-info/top_level.txt
cdk_constants-2.1.2.dist-info/RECORD
