Metadata-Version: 2.1
Name: cdk-constants
Version: 2.1.2
Summary: Library of helpful constants to work with the CDK
Home-page: https://github.com/kevinslin/cdk-constants
Author: Kevin S Lin<kevin@thence.io>
License: Apache-2.0
Project-URL: Source, https://github.com/kevinslin/cdk-constants
Platform: UNKNOWN
Classifier: Intended Audience :: Developers
Classifier: Operating System :: OS Independent
Classifier: Programming Language :: JavaScript
Classifier: Programming Language :: Python :: 3 :: Only
Classifier: Programming Language :: Python :: 3.6
Classifier: Programming Language :: Python :: 3.7
Classifier: Programming Language :: Python :: 3.8
Classifier: Typing :: Typed
Classifier: License :: OSI Approved
Requires-Python: >=3.6
Requires-Dist: jsii (~=0.20.11)
Requires-Dist: publication (>=0.0.3)
